magic_admin_django/__init__.py
magic_admin_django-0.0.0.0.dist-info/METADATA
magic_admin_django-0.0.0.0.dist-info/WHEEL
magic_admin_django-0.0.0.0.dist-info/top_level.txt
magic_admin_django-0.0.0.0.dist-info/RECORD
