Metadata-Version: 2.1
Name: magic-admin-django
Version: 0.0.0.0
Summary: Troll Goat
Home-page: https://magic.link
Author: Troll Goat
Author-email: arthur@magic.link
License: MIT
Platform: UNKNOWN
